ziet/__init__.py
ziet-0.1.0.dist-info/METADATA
ziet-0.1.0.dist-info/WHEEL
ziet-0.1.0.dist-info/top_level.txt
ziet-0.1.0.dist-info/RECORD
