Metadata-Version: 2.4
Name: ziet
Version: 0.1.0
Summary: A minimal utility package
Author: Ziet Labs
License: MIT
Project-URL: Homepage, https://docs.ziet.ai
Requires-Python: >=3.7
